yao/__init__.py
yao/__main__.py
yao/actor.py
yao/alerts.py
yao/commands.py
yao/controller.py
yao/delegate.py
yao/exceptions.py
yao/mech_commands.py
yao/mech_controller.py
yao/etc/BOSS_extra.acf
yao/etc/BOSS_extra_purge_erase_v2.acf
yao/etc/BOSS_extra_purge_erase_v3.acf
yao/etc/BOSS_extra_purge_erase_v4.acf
yao/etc/BOSS_extra_purge_erase_v5.acf
yao/etc/BOSS_extra_purge_erase_v6.acf
yao/etc/BOSS_extra_purge_erase_v8.acf
yao/etc/README.md
yao/etc/schema.json
yao/etc/yao.yml
sdss_yao-1.3.5.dist-info/METADATA
sdss_yao-1.3.5.dist-info/WHEEL
sdss_yao-1.3.5.dist-info/entry_points.txt
sdss_yao-1.3.5.dist-info/licenses/LICENSE.md
sdss_yao-1.3.5.dist-info/RECORD
