Metadata-Version: 2.4
Name: sdss-yao
Version: 1.3.5
Summary: BOSS spectrograph actor that uses an STA Archon controller
Project-URL: Homepage, https://github.com/sdss/yao
Project-URL: Repository, https://github.com/sdss/yao
Project-URL: Documentation, https://sdss-yao.readthedocs.org
Author-email: José Sánchez-Gallego <gallegoj@uw.edu>, Aidan Gray <aidan.gray@idg.jhu.edu>
License: BSD-3-Clause
License-File: LICENSE.md
Requires-Python: <4,>=3.10
Requires-Dist: sdss-archon>=0.15.5
